PolibasePersonAnswerAutomationService/__init__.py
PolibasePersonAnswerAutomationService/__main__.py
PolibasePersonAnswerAutomationService/const.py
PolibasePersonAnswerAutomationService/service.py
pih_plb_answ_auto-0.14.dist-info/METADATA
pih_plb_answ_auto-0.14.dist-info/WHEEL
pih_plb_answ_auto-0.14.dist-info/entry_points.txt
pih_plb_answ_auto-0.14.dist-info/top_level.txt
pih_plb_answ_auto-0.14.dist-info/RECORD
