Metadata-Version: 2.1
Name: pih-plb_answ_auto
Version: 0.14
Summary: PIH Polibase person answer automation service package
Home-page: https://pacifichosp.com/
Author: Nikita Karachentsev
Author-email: it@pacifichosp.com
License: MIT
Requires-Dist: ipih
